
[
  { "name": "Água Branca", "normalizedName": "agua branca", "lat": -9.26, "lon": -37.93 },
  { "name": "Anadia", "normalizedName": "anadia", "lat": -9.68, "lon": -36.3 },
  { "name": "Arapiraca", "normalizedName": "arapiraca", "lat": -9.75, "lon": -36.66 },
  { "name": "Atalaia", "normalizedName": "atalaia", "lat": -9.5, "lon": -36.02 },
  { "name": "Barra de Santo Antônio", "normalizedName": "barra de santo antonio", "lat": -9.4, "lon": -35.5 },
  { "name": "Barra de São Miguel", "normalizedName": "barra de sao miguel", "lat": -9.84, "lon": -35.9 },
  { "name": "Batalha", "normalizedName": "batalha", "lat": -9.67, "lon": -37.12 },
  { "name": "Belém", "normalizedName": "belem", "lat": -9.56, "lon": -36.52 },
  { "name": "Belo Monte", "normalizedName": "belo monte", "lat": -9.81, "lon": -37.26 },
  { "name": "Boca da Mata", "normalizedName": "boca da mata", "lat": -9.64, "lon": -36.22 },
  { "name": "Branquinha", "normalizedName": "branquinha", "lat": -9.22, "lon": -36.03 },
  { "name": "Cacimbinhas", "normalizedName": "cacimbinhas", "lat": -9.41, "lon": -37 },
  { "name": "Cajueiro", "normalizedName": "cajueiro", "lat": -9.39, "lon": -36.24 },
  { "name": "Campestre", "normalizedName": "campestre", "lat": -9.05, "lon": -35.56 },
  { "name": "Campo Alegre", "normalizedName": "campo alegre", "lat": -9.78, "lon": -36.35 },
  { "name": "Campo Grande", "normalizedName": "campo grande", "lat": -9.95, "lon": -36.79 },
  { "name": "Canapi", "normalizedName": "canapi", "lat": -9.11, "lon": -37.62 },
  { "name": "Capela", "normalizedName": "capela", "lat": -9.4, "lon": -36.07 },
  { "name": "Carneiros", "normalizedName": "carneiros", "lat": -9.35, "lon": -37.38 },
  { "name": "Chã Preta", "normalizedName": "cha preta", "lat": -9.23, "lon": -36.31 },
  { "name": "Coité do Nóia", "normalizedName": "coite do noia", "lat": -9.66, "lon": -36.56 },
  { "name": "Colônia Leopoldina", "normalizedName": "colonia leopoldina", "lat": -9.12, "lon": -35.71 },
  { "name": "Coqueiro Seco", "normalizedName": "coqueiro seco", "lat": -9.63, "lon": -35.79 },
  { "name": "Coruripe", "normalizedName": "coruripe", "lat": -10.12, "lon": -36.17 },
  { "name": "Craíbas", "normalizedName": "craibas", "lat": -9.59, "lon": -36.79 },
  { "name": "Delmiro Gouveia", "normalizedName": "delmiro gouveia", "lat": -9.38, "lon": -37.99 },
  { "name": "Dois Riachos", "normalizedName": "dois riachos", "lat": -9.38, "lon": -37.1 },
  { "name": "Estrela de Alagoas", "normalizedName": "estrela de alagoas", "lat": -9.42, "lon": -36.78 },
  { "name": "Feira Grande", "normalizedName": "feira grande", "lat": -9.89, "lon": -36.67 },
  { "name": "Feliz Deserto", "normalizedName": "feliz deserto", "lat": -10.29, "lon": -36.3 },
  { "name": "Flexeiras", "normalizedName": "flexeiras", "lat": -9.3, "lon": -35.71 },
  { "name": "Girau do Ponciano", "normalizedName": "girau do ponciano", "lat": -9.88, "lon": -36.73 },
  { "name": "Ibateguara", "normalizedName": "ibateguara", "lat": -9.1, "lon": -35.91 },
  { "name": "Igaci", "normalizedName": "igaci", "lat": -9.52, "lon": -36.63 },
  { "name": "Igreja Nova", "normalizedName": "igreja nova", "lat": -10.12, "lon": -36.66 },
  { "name": "Inhapi", "normalizedName": "inhapi", "lat": -9.22, "lon": -37.75 },
  { "name": "Jacaré dos Homens", "normalizedName": "jacare dos homens", "lat": -9.66, "lon": -37.17 },
  { "name": "Jacuípe", "normalizedName": "jacuipe", "lat": -9.04, "lon": -35.49 },
  { "name": "Japaratinga", "normalizedName": "japaratinga", "lat": -9.09, "lon": -35.25 },
  { "name": "Jaramataia", "normalizedName": "jaramataia", "lat": -9.66, "lon": -37.01 },
  { "name": "Jequiá da Praia", "normalizedName": "jequia da praia", "lat": -9.96, "lon": -36.03 },
  { "name": "Joaquim Gomes", "normalizedName": "joaquim gomes", "lat": -9.22, "lon": -35.79 },
  { "name": "Jundiá", "normalizedName": "jundia", "lat": -9.07, "lon": -35.61 },
  { "name": "Junqueiro", "normalizedName": "junqueiro", "lat": -9.88, "lon": -36.47 },
  { "name": "Lagoa da Canoa", "normalizedName": "lagoa da canoa", "lat": -9.83, "lon": -36.72 },
  { "name": "Limoeiro de Anadia", "normalizedName": "limoeiro de anadia", "lat": -9.74, "lon": -36.5 },
  { "name": "Maceió", "normalizedName": "maceio", "lat": -9.66, "lon": -35.73 },
  { "name": "Major Isidoro", "normalizedName": "major isidoro", "lat": -9.53, "lon": -36.98 },
  { "name": "Maragogi", "normalizedName": "maragogi", "lat": -9.01, "lon": -35.22 },
  { "name": "Maravilha", "normalizedName": "maravilha", "lat": -9.22, "lon": -37.36 },
  { "name": "Marechal Deodoro", "normalizedName": "marechal deodoro", "lat": -9.71, "lon": -35.89 },
  { "name": "Maribondo", "normalizedName": "maribondo", "lat": -9.56, "lon": -36.31 },
  { "name": "Mar Vermelho", "normalizedName": "mar vermelho", "lat": -9.43, "lon": -36.43 },
  { "name": "Mata Grande", "normalizedName": "mata grande", "lat": -9.1, "lon": -37.73 },
  { "name": "Matriz de Camaragibe", "normalizedName": "matriz de camaragibe", "lat": -9.17, "lon": -35.53 },
  { "name": "Messias", "normalizedName": "messias", "lat": -9.38, "lon": -35.84 },
  { "name": "Minador do Negrão", "normalizedName": "minador do negrao", "lat": -9.3, "lon": -36.87 },
  { "name": "Monteirópolis", "normalizedName": "monteiropolis", "lat": -9.61, "lon": -37.2 },
  { "name": "Murici", "normalizedName": "murici", "lat": -9.3, "lon": -35.94 },
  { "name": "Novo Lino", "normalizedName": "novo lino", "lat": -9.18, "lon": -35.66 },
  { "name": "Olho d'Água das Flores", "normalizedName": "olho d'agua das flores", "lat": -9.53, "lon": -37.29 },
  { "name": "Olho d'Água do Casado", "normalizedName": "olho d'agua do casado", "lat": -9.47, "lon": -37.83 },
  { "name": "Olho d'Água Grande", "normalizedName": "olho d'agua grande", "lat": -10, "lon": -36.81 },
  { "name": "Olivença", "normalizedName": "olivenca", "lat": -9.51, "lon": -37.19 },
  { "name": "Ouro Branco", "normalizedName": "ouro branco", "lat": -9.16, "lon": -37.38 },
  { "name": "Palestina", "normalizedName": "palestina", "lat": -9.66, "lon": -37.33 },
  { "name": "Palmeira dos Índios", "normalizedName": "palmeira dos indios", "lat": -9.4, "lon": -36.62 },
  { "name": "Pão de Açúcar", "normalizedName": "pao de acucar", "lat": -9.74, "lon": -37.43 },
  { "name": "Pariconha", "normalizedName": "pariconha", "lat": -9.26, "lon": -38.01 },
  { "name": "Paripueira", "normalizedName": "paripueira", "lat": -9.46, "lon": -35.55 },
  { "name": "Passo de Camaragibe", "normalizedName": "passo de camaragibe", "lat": -9.23, "lon": -35.49 },
  { "name": "Paulo Jacinto", "normalizedName": "paulo jacinto", "lat": -9.36, "lon": -36.36 },
  { "name": "Penedo", "normalizedName": "penedo", "lat": -10.29, "lon": -36.58 },
  { "name": "Piaçabuçu", "normalizedName": "piacabucu", "lat": -10.4, "lon": -36.43 },
  { "name": "Pilar", "normalizedName": "pilar", "lat": -9.59, "lon": -35.95 },
  { "name": "Pindoba", "normalizedName": "pindoba", "lat": -9.48, "lon": -36.29 },
  { "name": "Piranhas", "normalizedName": "piranhas", "lat": -9.62, "lon": -37.75 },
  { "name": "Poço das Trincheiras", "normalizedName": "poco das trincheiras", "lat": -9.26, "lon": -37.29 },
  { "name": "Porto Calvo", "normalizedName": "porto calvo", "lat": -9.15, "lon": -35.39 },
  { "name": "Porto de Pedras", "normalizedName": "porto de pedras", "lat": -9.15, "lon": -35.29 },
  { "name": "Porto Real do Colégio", "normalizedName": "porto real do colegio", "lat": -10.18, "lon": -36.84 },
  { "name": "Quebrangulo", "normalizedName": "quebrangulo", "lat": -9.29, "lon": -36.47 },
  { "name": "Rio Largo", "normalizedName": "rio largo", "lat": -9.47, "lon": -35.83 },
  { "name": "Roteiro", "normalizedName": "roteiro", "lat": -9.83, "lon": -35.98 },
  { "name": "Santa Luzia do Norte", "normalizedName": "santa luzia do norte", "lat": -9.6, "lon": -35.82 },
  { "name": "Santana do Ipanema", "normalizedName": "santana do ipanema", "lat": -9.37, "lon": -37.24 },
  { "name": "Santana do Mundaú", "normalizedName": "santana do mundau", "lat": -9.16, "lon": -36.21 },
  { "name": "São Brás", "normalizedName": "sao bras", "lat": -10.12, "lon": -36.94 },
  { "name": "São José da Laje", "normalizedName": "sao jose da laje", "lat": -9, "lon": -36.05 },
  { "name": "São José da Tapera", "normalizedName": "sao jose da tapera", "lat": -9.55, "lon": -37.38 },
  { "name": "São Luís do Quitunde", "normalizedName": "sao luis do quitunde", "lat": -9.32, "lon": -35.57 },
  { "name": "São Miguel dos Campos", "normalizedName": "sao miguel dos campos", "lat": -9.78, "lon": -36.09 },
  { "name": "São Miguel dos Milagres", "normalizedName": "sao miguel dos milagres", "lat": -9.26, "lon": -35.37 },
  { "name": "São Sebastião", "normalizedName": "sao sebastiao", "lat": -9.93, "lon": -36.55 },
  { "name": "Satuba", "normalizedName": "satuba", "lat": -9.56, "lon": -35.82 },
  { "name": "Senador Rui Palmeira", "normalizedName": "senador rui palmeira", "lat": -9.35, "lon": -37.52 },
  { "name": "Tanque d'Arca", "normalizedName": "tanque d'arca", "lat": -9.52, "lon": -36.44 },
  { "name": "Taquarana", "normalizedName": "taquarana", "lat": -9.68, "lon": -36.47 },
  { "name": "Teotônio Vilela", "normalizedName": "teotonio vilela", "lat": -9.93, "lon": -36.36 },
  { "name": "Traipu", "normalizedName": "traipu", "lat": -9.97, "lon": -37 },
  { "name": "União dos Palmares", "normalizedName": "uniao dos palmares", "lat": -9.16, "lon": -36.03 },
  { "name": "Viçosa", "normalizedName": "vicosa", "lat": -9.37, "lon": -36.24 }
]
