
[
  { "name": "Alvarães", "normalizedName": "alvaraes", "lat": -3.22, "lon": -64.8 },
  { "name": "Amaturá", "normalizedName": "amatura", "lat": -3.37, "lon": -68.19 },
  { "name": "Anamã", "normalizedName": "anama", "lat": -3.57, "lon": -61.4 },
  { "name": "Anori", "normalizedName": "anori", "lat": -3.77, "lon": -61.64 },
  { "name": "Apuí", "normalizedName": "apui", "lat": -7.19, "lon": -59.89 },
  { "name": "Atalaia do Norte", "normalizedName": "atalaia do norte", "lat": -4.37, "lon": -70.19 },
  { "name": "Autazes", "normalizedName": "autazes", "lat": -3.58, "lon": -59.13 },
  { "name": "Barcelos", "normalizedName": "barcelos", "lat": -0.97, "lon": -62.92 },
  { "name": "Barreirinha", "normalizedName": "barreirinha", "lat": -2.79, "lon": -57.07 },
  { "name": "Benjamin Constant", "normalizedName": "benjamin constant", "lat": -4.37, "lon": -70.03 },
  { "name": "Beruri", "normalizedName": "beruri", "lat": -3.9, "lon": -61.37 },
  { "name": "Boa Vista do Ramos", "normalizedName": "boa vista do ramos", "lat": -2.97, "lon": -57.59 },
  { "name": "Boca do Acre", "normalizedName": "boca do acre", "lat": -8.75, "lon": -67.39 },
  { "name": "Borba", "normalizedName": "borba", "lat": -4.38, "lon": -59.59 },
  { "name": "Caapiranga", "normalizedName": "caapiranga", "lat": -3.32, "lon": -61.2 },
  { "name": "Canutama", "normalizedName": "canutama", "lat": -6.53, "lon": -64.38 },
  { "name": "Carauari", "normalizedName": "carauari", "lat": -4.88, "lon": -66.89 },
  { "name": "Careiro", "normalizedName": "careiro", "lat": -3.76, "lon": -60.36 },
  { "name": "Careiro da Várzea", "normalizedName": "careiro da varzea", "lat": -3.2, "lon": -59.75 },
  { "name": "Coari", "normalizedName": "coari", "lat": -4.08, "lon": -63.14 },
  { "name": "Codajás", "normalizedName": "codajas", "lat": -3.83, "lon": -62.05 },
  { "name": "Eirunepé", "normalizedName": "eirunepe", "lat": -6.66, "lon": -69.87 },
  { "name": "Envira", "normalizedName": "envira", "lat": -7.3, "lon": -70.21 },
  { "name": "Fonte Boa", "normalizedName": "fonte boa", "lat": -2.51, "lon": -66.09 },
  { "name": "Guajará", "normalizedName": "guajara", "lat": -7.53, "lon": -72.58 },
  { "name": "Humaitá", "normalizedName": "humaita", "lat": -7.5, "lon": -63.02 },
  { "name": "Ipixuna", "normalizedName": "ipixuna", "lat": -7.05, "lon": -71.69 },
  { "name": "Iranduba", "normalizedName": "iranduba", "lat": -3.28, "lon": -60.18 },
  { "name": "Itacoatiara", "normalizedName": "itacoatiara", "lat": -3.14, "lon": -58.44 },
  { "name": "Itamarati", "normalizedName": "itamarati", "lat": -6.43, "lon": -68.25 },
  { "name": "Itapiranga", "normalizedName": "itapiranga", "lat": -2.92, "lon": -58.32 },
  { "name": "Japurá", "normalizedName": "japura", "lat": -1.82, "lon": -66.6 },
  { "name": "Juruá", "normalizedName": "jurua", "lat": -3.48, "lon": -66.07 },
  { "name": "Jutaí", "normalizedName": "jutai", "lat": -5.18, "lon": -68.9 },
  { "name": "Lábrea", "normalizedName": "labrea", "lat": -7.25, "lon": -64.79 },
  { "name": "Manacapuru", "normalizedName": "manacapuru", "lat": -3.3, "lon": -60.62 },
  { "name": "Manaquiri", "normalizedName": "manaquiri", "lat": -3.43, "lon": -60.46 },
  { "name": "Manaus", "normalizedName": "manaus", "lat": -3.11, "lon": -60.02 },
  { "name": "Manicoré", "normalizedName": "manicore", "lat": -5.8, "lon": -61.3 },
  { "name": "Maraã", "normalizedName": "maraa", "lat": -1.83, "lon": -65.57 },
  { "name": "Maués", "normalizedName": "maues", "lat": -3.38, "lon": -57.71 },
  { "name": "Nhamundá", "normalizedName": "nhamunda", "lat": -2.18, "lon": -56.71 },
  { "name": "Nova Olinda do Norte", "normalizedName": "nova olinda do norte", "lat": -3.88, "lon": -59.09 },
  { "name": "Novo Airão", "normalizedName": "novo airao", "lat": -2.62, "lon": -60.94 },
  { "name": "Novo Aripuanã", "normalizedName": "novo aripuana", "lat": -5.12, "lon": -60.38 },
  { "name": "Parintins", "normalizedName": "parintins", "lat": -2.62, "lon": -56.73 },
  { "name": "Pauini", "normalizedName": "pauini", "lat": -7.71, "lon": -66.97 },
  { "name": "Presidente Figueiredo", "normalizedName": "presidente figueiredo", "lat": -2.03, "lon": -60.02 },
  { "name": "Rio Preto da Eva", "normalizedName": "rio preto da eva", "lat": -2.69, "lon": -59.7 },
  { "name": "Santa Isabel do Rio Negro", "normalizedName": "santa isabel do rio negro", "lat": -0.41, "lon": -65.01 },
  { "name": "Santo Antônio do Içá", "normalizedName": "santo antonio do ica", "lat": -3.1, "lon": -67.94 },
  { "name": "São Gabriel da Cachoeira", "normalizedName": "sao gabriel da cachoeira", "lat": 0.13, "lon": -67.08 },
  { "name": "São Paulo de Olivença", "normalizedName": "sao paulo de olivenca", "lat": -3.37, "lon": -68.87 },
  { "name": "São Sebastião do Uatumã", "normalizedName": "sao sebastiao do uatuma", "lat": -2.57, "lon": -57.87 },
  { "name": "Silves", "normalizedName": "silves", "lat": -2.83, "lon": -58.21 },
  { "name": "Tabatinga", "normalizedName": "tabatinga", "lat": -4.25, "lon": -69.93 },
  { "name": "Tapauá", "normalizedName": "tapaua", "lat": -5.62, "lon": -63.18 },
  { "name": "Tefé", "normalizedName": "tefe", "lat": -3.35, "lon": -64.71 },
  { "name": "Tonantins", "normalizedName": "tonantins", "lat": -2.87, "lon": -67.8 },
  { "name": "Uarini", "normalizedName": "uarini", "lat": -2.99, "lon": -65.1 },
  { "name": "Urucará", "normalizedName": "urucara", "lat": -2.53, "lon": -57.76 },
  { "name": "Urucurituba", "normalizedName": "urucurituba", "lat": -3.13, "lon": -58.15 }
]
