
[
  { "name": "Abatiá", "normalizedName": "abatia", "lat": -23.303, "lon": -50.313 },
  { "name": "Adrianópolis", "normalizedName": "adrianopolis", "lat": -24.66, "lon": -48.991 },
  { "name": "Agudos do Sul", "normalizedName": "agudos do sul", "lat": -25.996, "lon": -49.336 },
  { "name": "Almirante Tamandaré", "normalizedName": "almirante tamandare", "lat": -25.325, "lon": -49.309 },
  { "name": "Altamira do Paraná", "normalizedName": "altamira do parana", "lat": -24.84, "lon": -52.695 },
  { "name": "Altônia", "normalizedName": "altonia", "lat": -23.876, "lon": -53.902 },
  { "name": "Alto Paraíso", "normalizedName": "alto paraiso", "lat": -23.364, "lon": -53.649 },
  { "name": "Alto Paraná", "normalizedName": "alto parana", "lat": -23.131, "lon": -52.316 },
  { "name": "Alto Piquiri", "normalizedName": "alto piquiri", "lat": -24.032, "lon": -53.473 },
  { "name": "Alvorada do Sul", "normalizedName": "alvorada do sul", "lat": -22.784, "lon": -51.229 },
  { "name": "Amaporã", "normalizedName": "amapora", "lat": -23.085, "lon": -52.716 },
  { "name": "Ampére", "normalizedName": "ampere", "lat": -25.918, "lon": -53.468 },
  { "name": "Anahy", "normalizedName": "anahy", "lat": -24.664, "lon": -53.138 },
  { "name": "Andirá", "normalizedName": "andira", "lat": -23.056, "lon": -50.228 },
  { "name": "Ângulo", "normalizedName": "angulo", "lat": -23.193, "lon": -51.916 },
  { "name": "Antonina", "normalizedName": "antonina", "lat": -25.428, "lon": -48.713 },
  { "name": "Antônio Olinto", "normalizedName": "antonio olinto", "lat": -25.986, "lon": -50.19 },
  { "name": "Apucarana", "normalizedName": "apucarana", "lat": -23.55, "lon": -51.46 },
  { "name": "Arapongas", "normalizedName": "arapongas", "lat": -23.419, "lon": -51.424 },
  { "name": "Arapoti", "normalizedName": "arapoti", "lat": -24.153, "lon": -49.79 },
  { "name": "Arapuã", "normalizedName": "arapua", "lat": -24.288, "lon": -51.776 },
  { "name": "Araruna", "normalizedName": "araruna", "lat": -23.929, "lon": -52.551 },
  { "name": "Araucária", "normalizedName": "araucaria", "lat": -25.592, "lon": -49.408 },
  { "name": "Ariranha do Ivaí", "normalizedName": "ariranha do ivai", "lat": -24.409, "lon": -51.584 },
  { "name": "Assaí", "normalizedName": "assai", "lat": -23.371, "lon": -50.841 },
  { "name": "Assis Chateaubriand", "normalizedName": "assis chateaubriand", "lat": -24.417, "lon": -53.522 },
  { "name": "Astorga", "normalizedName": "astorga", "lat": -23.232, "lon": -51.666 },
  { "name": "Atalaia", "normalizedName": "atalaia", "lat": -23.151, "lon": -52.054 },
  { "name": "Balsa Nova", "normalizedName": "balsa nova", "lat": -25.597, "lon": -49.63 },
  { "name": "Bandeirantes", "normalizedName": "bandeirantes", "lat": -23.109, "lon": -50.369 },
  { "name": "Barbosa Ferraz", "normalizedName": "barbosa ferraz", "lat": -24.225, "lon": -52.008 },
  { "name": "Barracão", "normalizedName": "barracao", "lat": -26.251, "lon": -53.63 },
  { "name": "Barra do Jacaré", "normalizedName": "barra do jacare", "lat": -23.136, "lon": -50.187 },
  { "name": "Bela Vista da Caroba", "normalizedName": "bela vista da caroba", "lat": -25.961, "lon": -53.676 },
  { "name": "Bela Vista do Paraíso", "normalizedName": "bela vista do paraiso", "lat": -22.996, "lon": -51.189 },
  { "name": "Bituruna", "normalizedName": "bituruna", "lat": -26.159, "lon": -51.554 },
  { "name": "Boa Esperança", "normalizedName": "boa esperanca", "lat": -24.28, "lon": -52.75 },
  { "name": "Boa Esperança do Iguaçu", "normalizedName": "boa esperanca do iguacu", "lat": -25.688, "lon": -53.278 },
  { "name": "Boa Ventura de São Roque", "normalizedName": "boa ventura de sao roque", "lat": -24.814, "lon": -51.986 },
  { "name": "Boa Vista da Aparecida", "normalizedName": "boa vista da aparecida", "lat": -25.421, "lon": -53.411 },
  { "name": "Bocaiúva do Sul", "normalizedName": "bocaiuva do sul", "lat": -25.176, "lon": -49.141 },
  { "name": "Bom Jesus do Sul", "normalizedName": "bom jesus do sul", "lat": -26.18, "lon": -53.585 },
  { "name": "Bom Sucesso", "normalizedName": "bom sucesso", "lat": -23.77, "lon": -51.782 },
  { "name": "Bom Sucesso do Sul", "normalizedName": "bom sucesso do sul", "lat": -26.068, "lon": -52.89 },
  { "name": "Borrazópolis", "normalizedName": "borrazopolis", "lat": -23.953, "lon": -51.602 },
  { "name": "Braganey", "normalizedName": "braganey", "lat": -24.77, "lon": -53.111 },
  { "name": "Brasilândia do Sul", "normalizedName": "brasilandia do sul", "lat": -24.167, "lon": -53.535 },
  { "name": "Cafeara", "normalizedName": "cafeara", "lat": -22.888, "lon": -51.705 },
  { "name": "Cafelândia", "normalizedName": "cafelandia", "lat": -24.636, "lon": -53.298 },
  { "name": "Cafezal do Sul", "normalizedName": "cafezal do sul", "lat": -23.858, "lon": -53.649 },
  { "name": "Califórnia", "normalizedName": "california", "lat": -23.648, "lon": -51.353 },
  { "name": "Cambará", "normalizedName": "cambara", "lat": -23.045, "lon": -50.073 },
  { "name": "Cambé", "normalizedName": "cambe", "lat": -23.276, "lon": -51.278 },
  { "name": "Cambira", "normalizedName": "cambira", "lat": -23.6, "lon": -51.572 },
  { "name": "Campina da Lagoa", "normalizedName": "campina da lagoa", "lat": -24.588, "lon": -52.545 },
  { "name": "Campina do Simão", "normalizedName": "campina do simao", "lat": -25.32, "lon": -51.789 },
  { "name": "Campina Grande do Sul", "normalizedName": "campina grande do sul", "lat": -25.303, "lon": -49.055 },
  { "name": "Campo Bonito", "normalizedName": "campo bonito", "lat": -25.04, "lon": -53.079 },
  { "name": "Campo do Tenente", "normalizedName": "campo do tenente", "lat": -25.981, "lon": -49.689 },
  { "name": "Campo Largo", "normalizedName": "campo largo", "lat": -25.459, "lon": -49.529 },
  { "name": "Campo Magro", "normalizedName": "campo magro", "lat": -25.356, "lon": -49.458 },
  { "name": "Campo Mourão", "normalizedName": "campo mourao", "lat": -24.043, "lon": -52.383 },
  { "name": "Cândido de Abreu", "normalizedName": "candido de abreu", "lat": -24.569, "lon": -51.336 },
  { "name": "Candói", "normalizedName": "candoi", "lat": -25.564, "lon": -52.029 },
  { "name": "Cantagalo", "normalizedName": "cantagalo", "lat": -25.378, "lon": -52.12 },
  { "name": "Capanema", "normalizedName": "capanema", "lat": -25.674, "lon": -53.805 },
  { "name": "Capitão Leônidas Marques", "normalizedName": "capitao leonidas marques", "lat": -25.485, "lon": -53.606 },
  { "name": "Carambeí", "normalizedName": "carambei", "lat": -24.915, "lon": -50.098 },
  { "name": "Carlópolis", "normalizedName": "carlopolis", "lat": -23.428, "lon": -49.718 },
  { "name": "Cascavel", "normalizedName": "cascavel", "lat": -24.955, "lon": -53.455 },
  { "name": "Castro", "normalizedName": "castro", "lat": -24.791, "lon": -50.011 },
  { "name": "Catanduvas", "normalizedName": "catanduvas", "lat": -25.263, "lon": -53.155 },
  { "name": "Centenário do Sul", "normalizedName": "centenario do sul", "lat": -22.846, "lon": -51.597 },
  { "name": "Cerro Azul", "normalizedName": "cerro azul", "lat": -24.819, "lon": -49.274 },
  { "name": "Céu Azul", "normalizedName": "ceu azul", "lat": -25.147, "lon": -53.844 },
  { "name": "Chopinzinho", "normalizedName": "chopinzinho", "lat": -25.85, "lon": -52.52 },
  { "name": "Cianorte", "normalizedName": "cianorte", "lat": -23.663, "lon": -52.605 },
  { "name": "Cidade Gaúcha", "normalizedName": "cidade gaucha", "lat": -23.38, "lon": -52.946 },
  { "name": "Clevelândia", "normalizedName": "clevelandia", "lat": -26.406, "lon": -52.35 },
  { "name": "Colombo", "normalizedName": "colombo", "lat": -25.291, "lon": -49.224 },
  { "name": "Colorado", "normalizedName": "colorado", "lat": -22.836, "lon": -51.974 },
  { "name": "Congonhinhas", "normalizedName": "congonhinhas", "lat": -23.551, "lon": -50.559 },
  { "name": "Conselheiro Mairinck", "normalizedName": "conselheiro mairinck", "lat": -23.633, "lon": -50.222 },
  { "name": "Contenda", "normalizedName": "contenda", "lat": -25.676, "lon": -49.531 },
  { "name": "Corbélia", "normalizedName": "corbelia", "lat": -24.798, "lon": -53.298 },
  { "name": "Cornélio Procópio", "normalizedName": "cornelio procopio", "lat": -23.18, "lon": -50.647 },
  { "name": "Coronel Domingos Soares", "normalizedName": "coronel domingos soares", "lat": -26.223, "lon": -52.036 },
  { "name": "Coronel Vivida", "normalizedName": "coronel vivida", "lat": -25.979, "lon": -52.571 },
  { "name": "Corumbataí do Sul", "normalizedName": "corumbatai do sul", "lat": -24.123, "lon": -52.096 },
  { "name": "Cruzeiro do Iguaçu", "normalizedName": "cruzeiro do iguacu", "lat": -25.597, "lon": -53.111 },
  { "name": "Cruzeiro do Oeste", "normalizedName": "cruzeiro do oeste", "lat": -23.78, "lon": -53.078 },
  { "name": "Cruzeiro do Sul", "normalizedName": "cruzeiro do sul", "lat": -22.956, "lon": -52.176 },
  { "name": "Cruz Machado", "normalizedName": "cruz machado", "lat": -26.016, "lon": -51.343 },
  { "name": "Cruzmaltina", "normalizedName": "cruzmaltina", "lat": -24.013, "lon": -51.488 },
  { "name": "Curitiba", "normalizedName": "curitiba", "lat": -25.429, "lon": -49.271 },
  { "name": "Curiúva", "normalizedName": "curiuva", "lat": -24.032, "lon": -50.457 },
  { "name": "Diamante do Norte", "normalizedName": "diamante do norte", "lat": -22.656, "lon": -52.863 },
  { "name": "Diamante do Sul", "normalizedName": "diamante do sul", "lat": -25.048, "lon": -52.709 },
  { "name": "Diamante D'Oeste", "normalizedName": "diamante d'oeste", "lat": -24.939, "lon": -54.026 },
  { "name": "Dois Vizinhos", "normalizedName": "dois vizinhos", "lat": -25.748, "lon": -53.056 },
  { "name": "Douradina", "normalizedName": "douradina", "lat": -23.385, "lon": -53.292 },
  { "name": "Doutor Camargo", "normalizedName": "doutor camargo", "lat": -23.551, "lon": -52.213 },
  { "name": "Doutor Ulysses", "normalizedName": "doutor ulysses", "lat": -24.582, "lon": -49.431 },
  { "name": "Enéas Marques", "normalizedName": "eneas marques", "lat": -25.961, "lon": -53.167 },
  { "name": "Engenheiro Beltrão", "normalizedName": "engenheiro beltrao", "lat": -23.797, "lon": -52.269 },
  { "name": "Esperança Nova", "normalizedName": "esperanca nova", "lat": -23.778, "lon": -53.792 },
  { "name": "Entre Rios do Oeste", "normalizedName": "entre rios do oeste", "lat": -24.708, "lon": -54.24 },
  { "name": "Espigão Alto do Iguaçu", "normalizedName": "espigao alto do iguacu", "lat": -25.474, "lon": -52.827 },
  { "name": "Farol", "normalizedName": "farol", "lat": -24.113, "lon": -52.285 },
  { "name": "Faxinal", "normalizedName": "faxinal", "lat": -24.001, "lon": -51.318 },
  { "name": "Fazenda Rio Grande", "normalizedName": "fazenda rio grande", "lat": -25.658, "lon": -49.309 },
  { "name": "Fênix", "normalizedName": "fenix", "lat": -23.905, "lon": -51.98 },
  { "name": "Fernandes Pinheiro", "normalizedName": "fernandes pinheiro", "lat": -25.424, "lon": -50.548 },
  { "name": "Figueira", "normalizedName": "figueira", "lat": -23.856, "lon": -50.407 },
  { "name": "Flor da Serra do Sul", "normalizedName": "flor da serra do sul", "lat": -26.261, "lon": -53.303 },
  { "name": "Floraí", "normalizedName": "florai", "lat": -23.3, "lon": -52.23 },
  { "name": "Floresta", "normalizedName": "floresta", "lat": -23.606, "lon": -52.083 },
  { "name": "Florestópolis", "normalizedName": "florestopolis", "lat": -22.862, "lon": -51.385 },
  { "name": "Flórida", "normalizedName": "florida", "lat": -23.097, "lon": -51.966 },
  { "name": "Formosa do Oeste", "normalizedName": "formosa do oeste", "lat": -24.316, "lon": -53.315 },
  { "name": "Foz do Iguaçu", "normalizedName": "foz do iguacu", "lat": -25.546, "lon": -54.588 },
  { "name": "Francisco Alves", "normalizedName": "francisco alves", "lat": -24.062, "lon": -53.84 },
  { "name": "Francisco Beltrão", "normalizedName": "francisco beltrao", "lat": -26.08, "lon": -53.053 },
  { "name": "Foz do Jordão", "normalizedName": "foz do jordao", "lat": -25.75, "lon": -52.126 },
  { "name": "General Carneiro", "normalizedName": "general carneiro", "lat": -26.425, "lon": -51.319 },
  { "name": "Godoy Moreira", "normalizedName": "godoy moreira", "lat": -24.18, "lon": -51.869 },
  { "name": "Goioerê", "normalizedName": "goioere", "lat": -24.18, "lon": -53.024 },
  { "name": "Goioxim", "normalizedName": "goioxim", "lat": -25.133, "lon": -51.966 },
  { "name": "Grandes Rios", "normalizedName": "grandes rios", "lat": -24.153, "lon": -51.493 },
  { "name": "Guaíra", "normalizedName": "guaira", "lat": -24.08, "lon": -54.256 },
  { "name": "Guairaçá", "normalizedName": "guairaca", "lat": -22.92, "lon": -52.72 },
  { "name": "Guamiranga", "normalizedName": "guamiranga", "lat": -25.215, "lon": -50.778 },
  { "name": "Guapirama", "normalizedName": "guapirama", "lat": -23.518, "lon": -50.046 },
  { "name": "Guaporema", "normalizedName": "guaporema", "lat": -23.329, "lon": -52.812 },
  { "name": "Guaraci", "normalizedName": "guaraci", "lat": -22.973, "lon": -51.666 },
  { "name": "Guaraniaçu", "normalizedName": "guaraniacu", "lat": -25.096, "lon": -52.877 },
  { "name": "Guarapuava", "normalizedName": "guarapuava", "lat": -25.395, "lon": -51.457 },
  { "name": "Guaraqueçaba", "normalizedName": "guaraquecaba", "lat": -25.311, "lon": -48.324 },
  { "name": "Guaratuba", "normalizedName": "guaratuba", "lat": -25.882, "lon": -48.574 },
  { "name": "Honório Serpa", "normalizedName": "honorio serpa", "lat": -26.126, "lon": -52.375 },
  { "name": "Ibaiti", "normalizedName": "ibaiti", "lat": -23.847, "lon": -50.386 },
  { "name": "Ibema", "normalizedName": "ibema", "lat": -25.138, "lon": -53.011 },
  { "name": "Ibiporã", "normalizedName": "ibipora", "lat": -23.267, "lon": -51.053 },
  { "name": "Icaraíma", "normalizedName": "icaraima", "lat": -23.396, "lon": -53.616 },
  { "name": "Iguaraçu", "normalizedName": "iguaracu", "lat": -23.167, "lon": -51.841 },
  { "name": "Iguatu", "normalizedName": "iguatu", "lat": -24.787, "lon": -53.25 },
  { "name": "Imbaú", "normalizedName": "imbau", "lat": -24.423, "lon": -50.758 },
  { "name": "Imbituva", "normalizedName": "imbituva", "lat": -25.228, "lon": -50.605 },
  { "name": "Inácio Martins", "normalizedName": "inacio martins", "lat": -25.568, "lon": -51.23 },
  { "name": "Inajá", "normalizedName": "inaja", "lat": -22.753, "lon": -52.271 },
  { "name": "Indianópolis", "normalizedName": "indianopolis", "lat": -23.491, "lon": -52.716 },
  { "name": "Ipiranga", "normalizedName": "ipiranga", "lat": -25.031, "lon": -50.584 },
  { "name": "Iporã", "normalizedName": "ipora", "lat": -24.009, "lon": -53.701 },
  { "name": "Iracema do Oeste", "normalizedName": "iracema do oeste", "lat": -24.478, "lon": -53.334 },
  { "name": "Irati", "normalizedName": "irati", "lat": -25.467, "lon": -50.651 },
  { "name": "Iretama", "normalizedName": "iretama", "lat": -24.421, "lon": -52.102 },
  { "name": "Itaguajé", "normalizedName": "itaguaje", "lat": -22.61, "lon": -51.96 },
  { "name": "Itaipulândia", "normalizedName": "itaipulandia", "lat": -25.385, "lon": -54.341 },
  { "name": "Itambaracá", "normalizedName": "itambaraca", "lat": -23.02, "lon": -50.581 },
  { "name": "Itambé", "normalizedName": "itambe", "lat": -23.673, "lon": -51.977 },
  { "name": "Itapejara d'Oeste", "normalizedName": "itapejara d'oeste", "lat": -25.969, "lon": -52.812 },
  { "name": "Itaperuçu", "normalizedName": "itaperucu", "lat": -25.218, "lon": -49.348 },
  { "name": "Itaúna do Sul", "normalizedName": "itauna do sul", "lat": -22.771, "lon": -52.923 },
  { "name": "Ivaí", "normalizedName": "ivai", "lat": -25.012, "lon": -50.85 },
  { "name": "Ivaiporã", "normalizedName": "ivaipora", "lat": -24.246, "lon": -51.652 },
  { "name": "Ivaté", "normalizedName": "ivate", "lat": -23.518, "lon": -53.47 },
  { "name": "Ivatuba", "normalizedName": "ivatuba", "lat": -23.633, "lon": -52.21 },
  { "name": "Jaboti", "normalizedName": "jaboti", "lat": -23.753, "lon": -50.068 },
  { "name": "Jacarezinho", "normalizedName": "jacarezinho", "lat": -23.161, "lon": -49.971 },
  { "name": "Jaguapitã", "normalizedName": "jaguapita", "lat": -23.097, "lon": -51.488 },
  { "name": "Jaguariaíva", "normalizedName": "jaguariaiva", "lat": -24.25, "lon": -49.706 },
  { "name": "Jandaia do Sul", "normalizedName": "jandaia do sul", "lat": -23.603, "lon": -51.644 },
  { "name": "Janiópolis", "normalizedName": "janiopolis", "lat": -24.137, "lon": -52.793 },
  { "name": "Japira", "normalizedName": "japira", "lat": -23.811, "lon": -50.141 },
  { "name": "Japurá", "normalizedName": "japura", "lat": -23.447, "lon": -52.56 },
  { "name": "Jardim Alegre", "normalizedName": "jardim alegre", "lat": -24.175, "lon": -51.688 },
  { "name": "Jardim Olinda", "normalizedName": "jardim olinda", "lat": -22.68, "lon": -52.54 },
  { "name": "Jataizinho", "normalizedName": "jataizinho", "lat": -23.256, "lon": -51.01 },
  { "name": "Jesuítas", "normalizedName": "jesuitas", "lat": -24.387, "lon": -53.385 },
  { "name": "Joaquim Távora", "normalizedName": "joaquim tavora", "lat": -23.507, "lon": -49.805 },
  { "name": "Jundiaí do Sul", "normalizedName": "jundiai do sul", "lat": -23.44, "lon": -50.25 },
  { "name": "Juranda", "normalizedName": "juranda", "lat": -24.417, "lon": -52.793 },
  { "name": "Jussara", "normalizedName": "jussara", "lat": -23.626, "lon": -52.463 },
  { "name": "Kaloré", "normalizedName": "kalore", "lat": -23.847, "lon": -51.666 },
  { "name": "Lapa", "normalizedName": "lapa", "lat": -25.769, "lon": -49.716 },
  { "name": "Laranjal", "normalizedName": "laranjal", "lat": -24.878, "lon": -52.368 },
  { "name": "Laranjeiras do Sul", "normalizedName": "laranjeiras do sul", "lat": -25.409, "lon": -52.414 },
  { "name": "Leópolis", "normalizedName": "leopolis", "lat": -23.08, "lon": -50.74 },
  { "name": "Lidianópolis", "normalizedName": "lidianopolis", "lat": -24.11, "lon": -51.65 },
  { "name": "Lindoeste", "normalizedName": "lindoeste", "lat": -25.263, "lon": -53.535 },
  { "name": "Loanda", "normalizedName": "loanda", "lat": -22.923, "lon": -53.136 },
  { "name": "Lobato", "normalizedName": "lobato", "lat": -22.956, "lon": -51.966 },
  { "name": "Londrina", "normalizedName": "londrina", "lat": -23.31, "lon": -51.162 },
  { "name": "Luiziana", "normalizedName": "luiziana", "lat": -24.341, "lon": -52.261 },
  { "name": "Lunardelli", "normalizedName": "lunardelli", "lat": -24.08, "lon": -51.722 },
  { "name": "Lupionópolis", "normalizedName": "lupionopolis", "lat": -22.753, "lon": -51.661 },
  { "name": "Mallet", "normalizedName": "mallet", "lat": -25.882, "lon": -50.819 },
  { "name": "Mamborê", "normalizedName": "mambore", "lat": -24.321, "lon": -52.531 },
  { "name": "Mandaguaçu", "normalizedName": "mandaguacu", "lat": -23.344, "lon": -52.096 },
  { "name": "Mandaguari", "normalizedName": "mandaguari", "lat": -23.546, "lon": -51.67 },
  { "name": "Mandirituba", "normalizedName": "mandirituba", "lat": -25.779, "lon": -49.328 },
  { "name": "Manfrinópolis", "normalizedName": "manfrinopolis", "lat": -26.096, "lon": -53.307 },
  { "name": "Mangueirinha", "normalizedName": "mangueirinha", "lat": -25.942, "lon": -52.176 },
  { "name": "Manoel Ribas", "normalizedName": "manoel ribas", "lat": -24.516, "lon": -51.662 },
  { "name": "Marechal Cândido Rondon", "normalizedName": "marechal candido rondon", "lat": -24.556, "lon": -54.056 },
  { "name": "Maria Helena", "normalizedName": "maria helena", "lat": -23.639, "lon": -53.204 },
  { "name": "Marialva", "normalizedName": "marialva", "lat": -23.483, "lon": -51.791 },
  { "name": "Marilândia do Sul", "normalizedName": "marilandia do sul", "lat": -23.755, "lon": -51.31 },
  { "name": "Marilena", "normalizedName": "marilena", "lat": -22.73, "lon": -53.03 },
  { "name": "Mariluz", "normalizedName": "mariluz", "lat": -24.01, "lon": -53.14 },
  { "name": "Maringá", "normalizedName": "maringa", "lat": -23.425, "lon": -51.938 },
  { "name": "Mariópolis", "normalizedName": "mariopolis", "lat": -26.353, "lon": -52.552 },
  { "name": "Maripá", "normalizedName": "maripa", "lat": -24.426, "lon": -53.83 },
  { "name": "Marmeleiro", "normalizedName": "marmeleiro", "lat": -26.148, "lon": -53.027 },
  { "name": "Marquinho", "normalizedName": "marquinho", "lat": -25.129, "lon": -52.253 },
  { "name": "Marumbi", "normalizedName": "marumbi", "lat": -23.766, "lon": -51.621 },
  { "name": "Matelândia", "normalizedName": "matelandia", "lat": -25.251, "lon": -53.99 },
  { "name": "Matinhos", "normalizedName": "matinhos", "lat": -25.819, "lon": -48.544 },
  { "name": "Mato Rico", "normalizedName": "mato rico", "lat": -24.77, "lon": -52.21 },
  { "name": "Mauá da Serra", "normalizedName": "maua da serra", "lat": -23.903, "lon": -51.228 },
  { "name": "Medianeira", "normalizedName": "medianeira", "lat": -25.297, "lon": -54.093 },
  { "name": "Mercedes", "normalizedName": "mercedes", "lat": -24.46, "lon": -54.16 },
  { "name": "Mirador", "normalizedName": "mirador", "lat": -23.24, "lon": -52.78 },
  { "name": "Miraselva", "normalizedName": "miraselva", "lat": -22.96, "lon": -51.52 },
  { "name": "Missal", "normalizedName": "missal", "lat": -25.08, "lon": -54.24 },
  { "name": "Moreira Sales", "normalizedName": "moreira sales", "lat": -24.05, "lon": -53.01 },
  { "name": "Morretes", "normalizedName": "morretes", "lat": -25.47, "lon": -48.83 },
  { "name": "Munhoz de Melo", "normalizedName": "munhoz de melo", "lat": -23.15, "lon": -51.78 },
  { "name": "Nossa Senhora das Graças", "normalizedName": "nossa senhora das gracas", "lat": -22.99, "lon": -51.79 },
  { "name": "Nova Aliança do Ivaí", "normalizedName": "nova alianca do ivai", "lat": -23.16, "lon": -52.61 },
  { "name": "Nova América da Colina", "normalizedName": "nova america da colina", "lat": -23.34, "lon": -50.68 },
  { "name": "Nova Aurora", "normalizedName": "nova aurora", "lat": -24.53, "lon": -53.25 },
  { "name": "Nova Cantu", "normalizedName": "nova cantu", "lat": -24.66, "lon": -52.56 },
  { "name": "Nova Esperança", "normalizedName": "nova esperanca", "lat": -23.18, "lon": -52.2 },
  { "name": "Nova Esperança do Sudoeste", "normalizedName": "nova esperanca do sudoeste", "lat": -25.88, "lon": -53.28 },
  { "name": "Nova Fátima", "normalizedName": "nova fatima", "lat": -23.41, "lon": -50.56 },
  { "name": "Nova Laranjeiras", "normalizedName": "nova laranjeiras", "lat": -25.3, "lon": -52.55 },
  { "name": "Nova Londrina", "normalizedName": "nova londrina", "lat": -22.76, "lon": -52.98 },
  { "name": "Nova Olímpia", "normalizedName": "nova olimpia", "lat": -23.47, "lon": -52.97 },
  { "name": "Nova Prata do Iguaçu", "normalizedName": "nova prata do iguacu", "lat": -25.75, "lon": -53.36 },
  { "name": "Nova Santa Bárbara", "normalizedName": "nova santa barbara", "lat": -23.15, "lon": -50.78 },
  { "name": "Nova Santa Rosa", "normalizedName": "nova santa rosa", "lat": -24.47, "lon": -53.97 },
  { "name": "Nova Tebas", "normalizedName": "nova tebas", "lat": -24.48, "lon": -51.98 },
  { "name": "Novo Itacolomi", "normalizedName": "novo itacolomi", "lat": -23.77, "lon": -51.52 },
  { "name": "Ortigueira", "normalizedName": "ortigueira", "lat": -24.2, "lon": -50.95 },
  { "name": "Ourizona", "normalizedName": "ourizona", "lat": -23.46, "lon": -52.2 },
  { "name": "Ouro Verde do Oeste", "normalizedName": "ouro verde do oeste", "lat": -24.78, "lon": -53.86 },
  { "name": "Paiçandu", "normalizedName": "paicandu", "lat": -23.45, "lon": -52.04 },
  { "name": "Palmas", "normalizedName": "palmas", "lat": -26.48, "lon": -51.99 },
  { "name": "Palmeira", "normalizedName": "palmeira", "lat": -25.42, "lon": -50 },
  { "name": "Palmital", "normalizedName": "palmital", "lat": -24.89, "lon": -52.2 },
  { "name": "Palotina", "normalizedName": "palotina", "lat": -24.28, "lon": -53.83 },
  { "name": "Paraíso do Norte", "normalizedName": "paraiso do norte", "lat": -23.27, "lon": -52.53 },
  { "name": "Paranacity", "normalizedName": "paranacity", "lat": -22.93, "lon": -52.15 },
  { "name": "Paranaguá", "normalizedName": "paranagua", "lat": -25.52, "lon": -48.5 },
  { "name": "Paranapoema", "normalizedName": "paranapoema", "lat": -22.63, "lon": -52.13 },
  { "name": "Paranavaí", "normalizedName": "paranavai", "lat": -23.08, "lon": -52.46 },
  { "name": "Pato Bragado", "normalizedName": "pato bragado", "lat": -24.62, "lon": -54.21 },
  { "name": "Pato Branco", "normalizedName": "pato branco", "lat": -26.22, "lon": -52.67 },
  { "name": "Paula Freitas", "normalizedName": "paula freitas", "lat": -26.21, "lon": -50.91 },
  { "name": "Paulo Frontin", "normalizedName": "paulo frontin", "lat": -26.01, "lon": -50.87 },
  { "name": "Peabiru", "normalizedName": "peabiru", "lat": -23.9, "lon": -52.34 },
  { "name": "Perobal", "normalizedName": "perobal", "lat": -23.9, "lon": -53.4 },
  { "name": "Pérola", "normalizedName": "perola", "lat": -23.8, "lon": -53.68 },
  { "name": "Pérola d'Oeste", "normalizedName": "perola d'oeste", "lat": -25.86, "lon": -53.74 },
  { "name": "Piên", "normalizedName": "pien", "lat": -26.1, "lon": -49.43 },
  { "name": "Pinhais", "normalizedName": "pinhais", "lat": -25.44, "lon": -49.19 },
  { "name": "Pinhalão", "normalizedName": "pinhalao", "lat": -23.79, "lon": -50.05 },
  { "name": "Pinhal de São Bento", "normalizedName": "pinhal de sao bento", "lat": -25.99, "lon": -53.49 },
  { "name": "Pinhão", "normalizedName": "pinhao", "lat": -25.69, "lon": -51.65 },
  { "name": "Piraí do Sul", "normalizedName": "pirai do sul", "lat": -24.52, "lon": -49.94 },
  { "name": "Piraquara", "normalizedName": "piraquara", "lat": -25.44, "lon": -49.06 },
  { "name": "Pitanga", "normalizedName": "pitanga", "lat": -24.75, "lon": -51.75 },
  { "name": "Pitangueiras", "normalizedName": "pitangueiras", "lat": -23.2, "lon": -51.58 },
  { "name": "Planaltina do Paraná", "normalizedName": "planaltina do parana", "lat": -23.01, "lon": -52.92 },
  { "name": "Planalto", "normalizedName": "planalto", "lat": -25.71, "lon": -53.76 },
  { "name": "Ponta Grossa", "normalizedName": "ponta grossa", "lat": -25.09, "lon": -50.16 },
  { "name": "Pontal do Paraná", "normalizedName": "pontal do parana", "lat": -25.65, "lon": -48.51 },
  { "name": "Porecatu", "normalizedName": "porecatu", "lat": -22.75, "lon": -51.37 },
  { "name": "Porto Amazonas", "normalizedName": "porto amazonas", "lat": -25.53, "lon": -49.9 },
  { "name": "Porto Barreiro", "normalizedName": "porto barreiro", "lat": -25.59, "lon": -52.42 },
  { "name": "Porto Rico", "normalizedName": "porto rico", "lat": -22.77, "lon": -53.26 },
  { "name": "Porto Vitória", "normalizedName": "porto vitoria", "lat": -26.16, "lon": -51.23 },
  { "name": "Prado Ferreira", "normalizedName": "prado ferreira", "lat": -23.05, "lon": -51.45 },
  { "name": "Pranchita", "normalizedName": "pranchita", "lat": -26.02, "lon": -53.73 },
  { "name": "Presidente Castelo Branco", "normalizedName": "presidente castelo branco", "lat": -23.28, "lon": -52.15 },
  { "name": "Primeiro de Maio", "normalizedName": "primeiro de maio", "lat": -22.85, "lon": -51.02 },
  { "name": "Prudentópolis", "normalizedName": "prudentopolis", "lat": -25.21, "lon": -50.97 },
  { "name": "Quarto Centenário", "normalizedName": "quarto centenario", "lat": -24.3, "lon": -53.07 },
  { "name": "Quatiguá", "normalizedName": "quatigua", "lat": -23.57, "lon": -49.91 },
  { "name": "Quatro Barras", "normalizedName": "quatro barras", "lat": -25.36, "lon": -49.07 },
  { "name": "Quatro Pontes", "normalizedName": "quatro pontes", "lat": -24.57, "lon": -54.08 },
  { "name": "Quedas do Iguaçu", "normalizedName": "quedas do iguacu", "lat": -25.45, "lon": -52.9 },
  { "name": "Querência do Norte", "normalizedName": "querencia do norte", "lat": -23.08, "lon": -53.48 },
  { "name": "Quinta do Sol", "normalizedName": "quinta do sol", "lat": -23.87, "lon": -52.12 },
  { "name": "Quitandinha", "normalizedName": "quitandinha", "lat": -25.87, "lon": -49.49 },
  { "name": "Ramilândia", "normalizedName": "ramilandia", "lat": -25.1, "lon": -54.03 },
  { "name": "Rancho Alegre", "normalizedName": "rancho alegre", "lat": -23.08, "lon": -50.91 },
  { "name": "Rancho Alegre D'Oeste", "normalizedName": "rancho alegre d'oeste", "lat": -24.28, "lon": -52.96 },
  { "name": "Realeza", "normalizedName": "realeza", "lat": -25.77, "lon": -53.52 },
  { "name": "Rebouças", "normalizedName": "reboucas", "lat": -25.61, "lon": -50.68 },
  { "name": "Renascença", "normalizedName": "renascenca", "lat": -26.15, "lon": -52.96 },
  { "name": "Reserva", "normalizedName": "reserva", "lat": -24.65, "lon": -50.85 },
  { "name": "Reserva do Iguaçu", "normalizedName": "reserva do iguacu", "lat": -25.83, "lon": -52.02 },
  { "name": "Ribeirão Claro", "normalizedName": "ribeirao claro", "lat": -23.16, "lon": -49.75 },
  { "name": "Ribeirão do Pinhal", "normalizedName": "ribeirao do pinhal", "lat": -23.41, "lon": -50.36 },
  { "name": "Rio Azul", "normalizedName": "rio azul", "lat": -25.73, "lon": -50.79 },
  { "name": "Rio Bom", "normalizedName": "rio bom", "lat": -23.75, "lon": -51.42 },
  { "name": "Rio Bonito do Iguaçu", "normalizedName": "rio bonito do iguacu", "lat": -25.53, "lon": -52.54 },
  { "name": "Rio Branco do Ivaí", "normalizedName": "rio branco do ivai", "lat": -24.32, "lon": -51.31 },
  { "name": "Rio Branco do Sul", "normalizedName": "rio branco do sul", "lat": -25.18, "lon": -49.31 },
  { "name": "Rio Negro", "normalizedName": "rio negro", "lat": -26.09, "lon": -49.79 },
  { "name": "Rolândia", "normalizedName": "rolandia", "lat": -23.31, "lon": -51.36 },
  { "name": "Roncador", "normalizedName": "roncador", "lat": -24.64, "lon": -52.28 },
  { "name": "Rondon", "normalizedName": "rondon", "lat": -23.41, "lon": -52.77 },
  { "name": "Rosário do Ivaí", "normalizedName": "rosario do ivai", "lat": -24.23, "lon": -51.27 },
  { "name": "Sabáudia", "normalizedName": "sabaudia", "lat": -23.3, "lon": -51.55 },
  { "name": "Salgado Filho", "normalizedName": "salgado filho", "lat": -26.16, "lon": -53.36 },
  { "name": "Salto do Itararé", "normalizedName": "salto do itarare", "lat": -23.61, "lon": -49.63 },
  { "name": "Salto do Lontra", "normalizedName": "salto do lontra", "lat": -25.78, "lon": -53.3 },
  { "name": "Santa Amélia", "normalizedName": "santa amelia", "lat": -23.25, "lon": -50.41 },
  { "name": "Santa Cecília do Pavão", "normalizedName": "santa cecilia do pavao", "lat": -23.51, "lon": -50.78 },
  { "name": "Santa Cruz de Monte Castelo", "normalizedName": "santa cruz de monte castelo", "lat": -23.21, "lon": -53.25 },
  { "name": "Santa Fé", "normalizedName": "santa fe", "lat": -23.01, "lon": -51.81 },
  { "name": "Santa Helena", "normalizedName": "santa helena", "lat": -24.85, "lon": -54.33 },
  { "name": "Santa Inês", "normalizedName": "santa ines", "lat": -22.68, "lon": -51.87 },
  { "name": "Santa Isabel do Ivaí", "normalizedName": "santa isabel do ivai", "lat": -23.01, "lon": -53.2 },
  { "name": "Santa Izabel do Oeste", "normalizedName": "santa izabel do oeste", "lat": -25.82, "lon": -53.48 },
  { "name": "Santa Lúcia", "normalizedName": "santa lucia", "lat": -25.4, "lon": -53.58 },
  { "name": "Santa Maria do Oeste", "normalizedName": "santa maria do oeste", "lat": -24.91, "lon": -51.87 },
  { "name": "Santa Mariana", "normalizedName": "santa mariana", "lat": -23.14, "lon": -50.57 },
  { "name": "Santa Mônica", "normalizedName": "santa monica", "lat": -23.18, "lon": -53.11 },
  { "name": "Santana do Itararé", "normalizedName": "santana do itarare", "lat": -23.75, "lon": -49.56 },
  { "name": "Santa Tereza do Oeste", "normalizedName": "santa tereza do oeste", "lat": -25.07, "lon": -53.64 },
  { "name": "Santa Terezinha de Itaipu", "normalizedName": "santa terezinha de itaipu", "lat": -25.43, "lon": -54.4 },
  { "name": "Santo Antônio da Platina", "normalizedName": "santo antonio da platina", "lat": -23.29, "lon": -50.07 },
  { "name": "Santo Antônio do Caiuá", "normalizedName": "santo antonio do caiua", "lat": -22.72, "lon": -52.34 },
  { "name": "Santo Antônio do Paraíso", "normalizedName": "santo antonio do paraiso", "lat": -23.49, "lon": -50.64 },
  { "name": "Santo Antônio do Sudoeste", "normalizedName": "santo antonio do sudoeste", "lat": -26.07, "lon": -53.72 },
  { "name": "Santo Inácio", "normalizedName": "santo inacio", "lat": -22.7, "lon": -51.8 },
  { "name": "São Carlos do Ivaí", "normalizedName": "sao carlos do ivai", "lat": -23.32, "lon": -52.45 },
  { "name": "São Jerônimo da Serra", "normalizedName": "sao jeronimo da serra", "lat": -23.72, "lon": -50.75 },
  { "name": "São Jorge d'Oeste", "normalizedName": "sao jorge d'oeste", "lat": -25.7, "lon": -52.91 },
  { "name": "São Jorge do Ivaí", "normalizedName": "sao jorge do ivai", "lat": -23.5, "lon": -52.31 },
  { "name": "São Jorge do Patrocínio", "normalizedName": "sao jorge do patrocinio", "lat": -23.77, "lon": -53.86 },
  { "name": "São João", "normalizedName": "sao joao", "lat": -25.82, "lon": -52.73 },
  { "name": "São João do Caiuá", "normalizedName": "sao joao do caiua", "lat": -22.86, "lon": -52.33 },
  { "name": "São João do Ivaí", "normalizedName": "sao joao do ivai", "lat": -23.98, "lon": -51.82 },
  { "name": "São João do Triunfo", "normalizedName": "sao joao do triunfo", "lat": -25.68, "lon": -50.31 },
  { "name": "São José da Boa Vista", "normalizedName": "sao jose da boa vista", "lat": -23.89, "lon": -49.69 },
  { "name": "São José das Palmeiras", "normalizedName": "sao jose das palmeiras", "lat": -24.81, "lon": -54.07 },
  { "name": "São José dos Pinhais", "normalizedName": "sao jose dos pinhais", "lat": -25.53, "lon": -49.2 },
  { "name": "São Manoel do Paraná", "normalizedName": "sao manoel do parana", "lat": -23.41, "lon": -52.68 },
  { "name": "São Mateus do Sul", "normalizedName": "sao mateus do sul", "lat": -25.86, "lon": -50.38 },
  { "name": "São Miguel do Iguaçu", "normalizedName": "sao miguel do iguacu", "lat": -25.34, "lon": -54.24 },
  { "name": "São Pedro do Iguaçu", "normalizedName": "sao pedro do iguacu", "lat": -24.91, "lon": -53.84 },
  { "name": "São Pedro do Ivaí", "normalizedName": "sao pedro do ivai", "lat": -23.85, "lon": -51.88 },
  { "name": "São Pedro do Paraná", "normalizedName": "sao pedro do parana", "lat": -22.82, "lon": -53.22 },
  { "name": "São Sebastião da Amoreira", "normalizedName": "sao sebastiao da amoreira", "lat": -23.46, "lon": -50.76 },
  { "name": "São Tomé", "normalizedName": "sao tome", "lat": -23.53, "lon": -52.59 },
  { "name": "Sapopema", "normalizedName": "sapopema", "lat": -23.9, "lon": -50.57 },
  { "name": "Sarandi", "normalizedName": "sarandi", "lat": -23.44, "lon": -51.87 },
  { "name": "Saudade do Iguaçu", "normalizedName": "saudade do iguacu", "lat": -25.68, "lon": -52.61 },
  { "name": "Sengés", "normalizedName": "senges", "lat": -24.11, "lon": -49.46 },
  { "name": "Serranópolis do Iguaçu", "normalizedName": "serranopolis do iguacu", "lat": -25.37, "lon": -54.06 },
  { "name": "Sertaneja", "normalizedName": "sertaneja", "lat": -22.95, "lon": -50.83 },
  { "name": "Sertanópolis", "normalizedName": "sertanopolis", "lat": -22.95, "lon": -51.04 },
  { "name": "Siqueira Campos", "normalizedName": "siqueira campos", "lat": -23.69, "lon": -49.82 },
  { "name": "Sulina", "normalizedName": "sulina", "lat": -25.96, "lon": -52.79 },
  { "name": "Tamarana", "normalizedName": "tamarana", "lat": -23.77, "lon": -51.08 },
  { "name": "Tamboara", "normalizedName": "tamboara", "lat": -23.01, "lon": -52.5 },
  { "name": "Tapejara", "normalizedName": "tapejara", "lat": -23.73, "lon": -52.87 },
  { "name": "Tapira", "normalizedName": "tapira", "lat": -23.59, "lon": -53.08 },
  { "name": "Teixeira Soares", "normalizedName": "teixeira soares", "lat": -25.37, "lon": -50.45 },
  { "name": "Telêmaco Borba", "normalizedName": "telemaco borba", "lat": -24.32, "lon": -50.61 },
  { "name": "Terra Boa", "normalizedName": "terra boa", "lat": -23.76, "lon": -52.44 },
  { "name": "Terra Rica", "normalizedName": "terra rica", "lat": -22.71, "lon": -52.61 },
  { "name": "Terra Roxa", "normalizedName": "terra roxa", "lat": -24.16, "lon": -54.09 },
  { "name": "Tibagi", "normalizedName": "tibagi", "lat": -24.51, "lon": -50.41 },
  { "name": "Tijucas do Sul", "normalizedName": "tijucas do sul", "lat": -25.92, "lon": -49.19 },
  { "name": "Toledo", "normalizedName": "toledo", "lat": -24.71, "lon": -53.74 },
  { "name": "Tomazina", "normalizedName": "tomazina", "lat": -23.78, "lon": -49.95 },
  { "name": "Três Barras do Paraná", "normalizedName": "tres barras do parana", "lat": -25.42, "lon": -53.18 },
  { "name": "Tunas do Paraná", "normalizedName": "tunas do parana", "lat": -24.86, "lon": -49.03 },
  { "name": "Tuneiras do Oeste", "normalizedName": "tuneiras do oeste", "lat": -23.86, "lon": -52.89 },
  { "name": "Tupãssi", "normalizedName": "tupassi", "lat": -24.59, "lon": -53.5 },
  { "name": "Turvo", "normalizedName": "turvo", "lat": -25.04, "lon": -51.52 },
  { "name": "Ubiratã", "normalizedName": "ubirata", "lat": -24.53, "lon": -52.98 },
  { "name": "Umuarama", "normalizedName": "umuarama", "lat": -23.76, "lon": -53.32 },
  { "name": "União da Vitória", "normalizedName": "uniao da vitoria", "lat": -26.23, "lon": -51.08 },
  { "name": "Uniflor", "normalizedName": "uniflor", "lat": -22.95, "lon": -52.17 },
  { "name": "Uraí", "normalizedName": "urai", "lat": -23.2, "lon": -50.79 },
  { "name": "Wenceslau Braz", "normalizedName": "wenceslau braz", "lat": -23.87, "lon": -49.8 },
  { "name": "Ventania", "normalizedName": "ventania", "lat": -24.24, "lon": -50.24 },
  { "name": "Vera Cruz do Oeste", "normalizedName": "vera cruz do oeste", "lat": -25.07, "lon": -53.91 },
  { "name": "Verê", "normalizedName": "vere", "lat": -25.87, "lon": -52.9 },
  { "name": "Virmond", "normalizedName": "virmond", "lat": -25.39, "lon": -52.2 },
  { "name": "Vitorino", "normalizedName": "vitorino", "lat": -26.27, "lon": -52.78 },
  { "name": "Xambrê", "normalizedName": "xambre", "lat": -23.72, "lon": -53.53 }
]
